.gitignore
.pylintrc
AUTHORS.md
CHANGELOG.md
CONTRIBUTING.md
LICENSE
MANIFEST.in
README.md
setup.cfg
setup.py
.github/FUNDING.yml
.github/PULL_REQUEST_TEMPLATE.md
.github/codespell_ignore_words.txt
deid_data/__init__.py
deid_data/version.py
deid_data.egg-info/PKG-INFO
deid_data.egg-info/SOURCES.txt
deid_data.egg-info/dependency_links.txt
deid_data.egg-info/requires.txt
deid_data.egg-info/top_level.txt
deid_data/data/README.md
deid_data/data/__init__.py
deid_data/data/animals/cat.dcm
deid_data/data/dicom-cookies/image1.dcm
deid_data/data/dicom-cookies/image2.dcm
deid_data/data/dicom-cookies/image3.dcm
deid_data/data/dicom-cookies/image4.dcm
deid_data/data/dicom-cookies/image5.dcm
deid_data/data/dicom-cookies/image6.dcm
deid_data/data/dicom-cookies/image7.dcm
deid_data/data/humans/ctbrain1.dcm
deid_data/data/humans/ctbrain2.dcm
deid_data/data/ultrasounds/GREYSCALE_CINE.zip
deid_data/data/ultrasounds/GREYSCALE_IMAGE.dcm
deid_data/data/ultrasounds/RGB_CINE.zip
deid_data/data/ultrasounds/RGB_IMAGE.dcm
deid_data/data/ultrasounds/ultrasound-multiframe.dcm