Metadata-Version: 2.1
Name: deid-data
Version: 0.0.20
Summary: data to support deid, best effort deidentify dicom with python and pydicom
Home-page: https://github.com/pydicom/deid-data
Author: Vanessa Sochat
Author-email: vsoch@users.noreply.github.com
License: LICENSE
Keywords: open source,python,anonymize,dicom
Classifier: Development Status :: 5 - Production/Stable
Classifier: Environment :: Console
Classifier: Intended Audience :: Developers
Classifier: Intended Audience :: System Administrators
Classifier: Intended Audience :: Science/Research
Classifier: License :: OSI Approved :: MIT License
Classifier: Natural Language :: English
Classifier: Operating System :: Unix
Classifier: Programming Language :: Python
Classifier: Programming Language :: Python :: 3
Classifier: Topic :: Software Development
Classifier: Topic :: Scientific/Engineering
Classifier: Topic :: System :: Shells
Classifier: Topic :: Terminals
Classifier: Topic :: Utilities
License-File: LICENSE
License-File: AUTHORS.md
